Metadata-Version: 2.1
Name: urban-scraper
Version: 1.2
Summary: Easy to use Urban Dictionary asynchronous and synchronous scraper.
Home-page: https://github.com/m-y-x-i/urban-scraper
Author: Myxi
Author-email: myxi@duck.com
License: GNU GPLv3
Platform: UNKNOWN
Requires-Python: >=3.9
